hydra/__init__.py
hydra/cli.py
hydra/version.py
hydra/cloud/__init__.py
hydra/cloud/abstract_platform.py
hydra/cloud/aws_platform.py
hydra/cloud/fast_local_platform.py
hydra/cloud/google_cloud_platform.py
hydra/cloud/local_platform.py
hydra/resources/__init__.py
hydra/resources/gcp_machines.py
hydra/utils/__init__.py
hydra/utils/constants.py
hydra/utils/git.py
hydra/utils/git_repo.py
hydra/utils/storage.py
hydra/utils/utils.py
hydra_ml-0.3.9.data/scripts/gcp_execution.sh
hydra_ml-0.3.9.data/scripts/local_execution.sh
tests/__init__.py
tests/test_cil.py
tests/test_git_repo.py
hydra_ml-0.3.9.dist-info/LICENSE
hydra_ml-0.3.9.dist-info/METADATA
hydra_ml-0.3.9.dist-info/WHEEL
hydra_ml-0.3.9.dist-info/entry_points.txt
hydra_ml-0.3.9.dist-info/top_level.txt
hydra_ml-0.3.9.dist-info/RECORD
