Metadata-Version: 2.1
Name: hydra-ml
Version: 0.3.9
Summary: A cloud-agnostic ML Platform
Home-page: https://github.com/georgianpartners/hydra
Author: Hydra Development Team
Author-email: faisal.anees@georgian.io
License: UNKNOWN
Platform: UNKNOWN
Classifier: Programming Language :: Python :: 3
Classifier: License :: OSI Approved :: Apache Software License
Classifier: Operating System :: OS Independent
Classifier: Topic :: Scientific/Engineering :: Artificial Intelligence
Requires-Python: >=3.6
Requires-Dist: future-fstrings (==1.2.0)
Requires-Dist: click (==7.1.2)
Requires-Dist: pytest (==6.1.1)
Requires-Dist: pytest-mock (==3.3.1)
Requires-Dist: GitPython (==3.1.9)
Requires-Dist: google-cloud-storage (==1.32.0)
Requires-Dist: docker (==4.3.1)
Requires-Dist: pyyaml
Requires-Dist: boto3 (==1.16.28)
